model_hosting_container_standards/__init__.py
model_hosting_container_standards/common/__init__.py
model_hosting_container_standards/common/custom_code_ref_resolver/__init__.py
model_hosting_container_standards/common/custom_code_ref_resolver/file_loader.py
model_hosting_container_standards/common/custom_code_ref_resolver/function_loader.py
model_hosting_container_standards/common/custom_code_ref_resolver/module_loader.py
model_hosting_container_standards/common/fastapi/__init__.py
model_hosting_container_standards/common/fastapi/config.py
model_hosting_container_standards/common/fastapi/middleware/__init__.py
model_hosting_container_standards/common/fastapi/middleware/core.py
model_hosting_container_standards/common/fastapi/middleware/decorators.py
model_hosting_container_standards/common/fastapi/middleware/registry.py
model_hosting_container_standards/common/fastapi/middleware/source/__init__.py
model_hosting_container_standards/common/fastapi/middleware/source/base.py
model_hosting_container_standards/common/fastapi/middleware/source/decorator_loader.py
model_hosting_container_standards/common/fastapi/middleware/source/environment_loader.py
model_hosting_container_standards/common/fastapi/routing.py
model_hosting_container_standards/common/fastapi/utils.py
model_hosting_container_standards/common/handler/__init__.py
model_hosting_container_standards/common/handler/decorators.py
model_hosting_container_standards/common/handler/registry.py
model_hosting_container_standards/common/handler/resolver.py
model_hosting_container_standards/common/handler/spec/__init__.py
model_hosting_container_standards/common/handler/spec/parser.py
model_hosting_container_standards/common/transforms/BASE_FACTORY_USAGE.md
model_hosting_container_standards/common/transforms/__init__.py
model_hosting_container_standards/common/transforms/base_api_transform.py
model_hosting_container_standards/common/transforms/base_factory.py
model_hosting_container_standards/common/transforms/utils.py
model_hosting_container_standards-0.1.12.dist-info/METADATA
model_hosting_container_standards-0.1.12.dist-info/WHEEL
model_hosting_container_standards-0.1.12.dist-info/entry_points.txt
model_hosting_container_standards-0.1.12.dist-info/RECORD
