Metadata-Version: 2.4
Name: model-hosting-container-standards
Version: 0.1.12
Summary: Python toolkit for standardized model hosting container implementations with Amazon SageMaker integration
License: Apache-2.0
Author: Amazon Web Services
Requires-Python: >=3.10
Classifier: License :: OSI Approved :: Apache Software License
Classifier: Programming Language :: Python :: 3
Classifier: Programming Language :: Python :: 3.10
Classifier: Programming Language :: Python :: 3.11
Classifier: Programming Language :: Python :: 3.12
Classifier: Programming Language :: Python :: 3.13
Classifier: Programming Language :: Python :: 3.14
Requires-Dist: fastapi
Requires-Dist: httpx
Requires-Dist: jmespath
Requires-Dist: pydantic
Requires-Dist: setuptools
Requires-Dist: starlette (>=0.49.1)
Requires-Dist: supervisor (>=4.2.0)
